tests/__init__.py
tests/test_cli.py
tests/test_commands.py
tests/test_utils.py
tests/test_validators.py
tests/test_version.py
tests/utils.py
toil_cvflag/VERSION
toil_cvflag/__init__.py
toil_cvflag/__main__.py
toil_cvflag/cli.py
toil_cvflag/commands.py
toil_cvflag/exceptions.py
toil_cvflag/utils.py
toil_cvflag/validators.py
toil_cvflag/caveman_utils/cgpFlagCaVEMan_custom.pl
toil_cvflag/caveman_utils/flag.to.vcf.custom.convert.ini
toil_cvflag/caveman_utils/flag.vcf.custom.config.ini
toil_cvflag/data/README.md
toil_cvflag-1.0.0.dist-info/LICENSE
toil_cvflag-1.0.0.dist-info/METADATA
toil_cvflag-1.0.0.dist-info/WHEEL
toil_cvflag-1.0.0.dist-info/entry_points.txt
toil_cvflag-1.0.0.dist-info/top_level.txt
toil_cvflag-1.0.0.dist-info/RECORD
