Metadata-Version: 2.1
Name: toil-cvflag
Version: 1.0.0
Summary: A toil implementation of caveman flagging for vcf files.
Home-page: https://github.com/papaemmelab/toil_cvflag
Author: Juan S. Medina, Juan E. Arango
License: BSD
Platform: UNKNOWN
Classifier: Intended Audience :: Developers
Classifier: Intended Audience :: Science/Research
Classifier: License :: OSI Approved :: MIT License
Classifier: Natural Language :: English
Classifier: Operating System :: Unix
Classifier: Operating System :: POSIX
Classifier: Programming Language :: Python :: 2 :: Only
Classifier: Topic :: Utilities
Requires-Dist: docker (==2.5.1)
Requires-Dist: toil-container (>=1.1.0)
Provides-Extra: test
Requires-Dist: coverage (>=4.4.2) ; extra == 'test'
Requires-Dist: pydocstyle (>=2.1.1) ; extra == 'test'
Requires-Dist: pytest (==3.7.4) ; extra == 'test'
Requires-Dist: pytest-env (==0.6.2) ; extra == 'test'
Requires-Dist: pytest-sugar (>=0.9.1) ; extra == 'test'
Requires-Dist: pylint (>=1.8.1) ; extra == 'test'
Requires-Dist: requests (==2.18.4) ; extra == 'test'
Requires-Dist: tox (==2.9.1) ; extra == 'test'
